Booths_Multiplier.v
//Problem Statement : Write a Verilog module to multiply Two 4 bit signed numbers using Booth's algorithm 
//			i.   A, M and Q Three 5 bit shift Registers to be used 
//			ii.  M is multiplier and Q is Multiplicand 
//			iii. A will be temporary register. 
//			iv. The final Result will be stored in both A and Q 
// 			v.  The design should be implemented using a data path and a control path.   
//==============================================================================================
// File Name : Booths_Multiplier.v 
// Type 	: MVM + TVM 
// Author 	: Debayan Mazumdar                   | Nishad P Potdar 
// Mail 	: debayanmazumdar0@gmail.com | nishadppotdar09@gmail.com 
//==============================================================================================
// Release History 
// Version 1.0 	11/09/2022	
// ==============================================================================================
// Keywords : Booth's Multiplier, Signed 4-bit Numbers 
// ==============================================================================================
// MVM : 

//Shift Register 
module shift_reg (dout, din, sin, ld, shift, clr, clk);  
	//Port Section 
	input [4:0] din ;
	input sin, ld, shift, clk, clr ;
	output reg [4:0] dout ; 
	
	always @ (posedge clk)
		if (clr)
			dout <= 5'b0 ;
		else if(ld)   					// If Load signal is high the data from the bus will be loaded. 
			dout <= din ;
		else if (shift)					// If Shift signal is high then bits will be shifted serially. 
			dout <= {sin, dout[4:1]} ;
endmodule 

//PIPO Shift Register 
module PIPO (pout, pin, ldP, clk) ; 
	//Port Section 
	input [4:0] pin ;
	input ldP, clk ;
	output reg [4:0] pout ; 
		
	always @ (posedge clk)	
		if(ldP)						// If Load signal is high the data from the bus will be loaded. 
			pout <= pin ; 
endmodule 

//D Flip Flop 
module d_ff (q, d, clrd, clk); 				// D FF is used to store the Qm1 bit. 
	//Port Section
	input d, clrd, clk ; 
	output reg q ;
		
	always @ (posedge clk)
		if (clrd)					// If Clr is high FF will be cleared else the value of D will be loaded. 
			q <= 0 ;
		else 
			q <= d ;
endmodule 

//ALU     
module ALU (out, a, b, sel) ;				// The ALU is assigned the operation of addition or subtraction depending on the sel. 
	//Port Section 
	input [4:0] a, b ;
	input sel ;
	output reg [4:0] out; 
	
	always @ (*)
		if (sel)
			out = a + b ;
		else
			out = a - b ; 
endmodule 

//Counter 
module CNTR (cout, ldC, decC, clk); 			// This down counter is used to count the number of cycles to be executed.  
	//Port Section 
	input decC, clk, ldC ; 
	output reg [2:0] cout ;

	always @(posedge clk)
		if (ldC ==1'b1)
			cout <= 3'b101 ; 			//The inital value loaded in counter will be same as that of the number of bits (here 5 bit).
		else if (decC)
			cout <= cout - 1 ;
endmodule 

//Data Path 
module booth_data_path (iszero, qm1, q0, decr, ldcount, shiftA, ldA, clrA, ldM, ldQ, clrQ, shiftQ, clrff, data_in, addsub, clk) ;
	//Port Section 
	input  decr, ldcount, shiftA, ldA, clrA, ldM, ldQ, clrQ, shiftQ, clrff, addsub, clk ; 
	input [4:0] data_in ;
	output iszero, qm1, q0 ;
	wire  [4:0] A, M, Q, Z ;
	wire  [2:0] count ;
	
	assign iszero = ~| count ;  				// The iszero will be set once the count reaches to zero (3'b000)
	assign q0 = Q[0] ; 					// The LSB of Register QSR will be loaded into q0 which will act as input to flip flop. 
	
	// Module Instantiation 
	shift_reg QSR   (Q, data_in, A[0], ldQ, shiftQ, clrQ, clk) ;   // Reg Q
	shift_reg ASR   (A, Z, A[4], ldA, shiftA, clrA, clk) ;		// Reg A	
	PIPO     MPR   (M, data_in, ldM, clk) ; 			//Reg M 
	d_ff     QM  (qm1, q0, clrff, clk) ;				//D Flip Flop (for qm1)
	ALU   ALU (Z, A, M, addsub) ;					//ALU
	CNTR CNT (count, ldcount, decr, clk) ;			//Counter 
endmodule 

//Control Path 
module booth_control_path (iszero, qm1,q0, decr, ldcount, shiftA, ldA, clrA, ldM, ldQ, clrQ, shiftQ, clrff, data_in, addsub, clk, start, done) ;
	//Port Section
	output reg decr, ldcount, shiftA, ldA, clrA, ldM, ldQ, clrQ, shiftQ, clrff, addsub, done ;  
	input start, iszero, qm1, q0, clk ; 
	input[4:0] data_in  ;
	reg[2:0] state ;
	
	//States
	parameter 	S0 = 3'b000 , 
			S1 = 3'b001 , 
			S2 = 3'b010 ,
			S3 = 3'b011 ,
			S4 = 3'b100 ,
			S5 = 3'b101 ,
			S6 = 3'b110 ;

	always@ (posedge clk) 
	
	//Implementation of State Diagram of control path 
	case (state)
		S0 	: 	if (start) state <= S1 ;
		S1 	: 	state <= S2 ;
		S2 	: 	#2 if ({q0, qm1} == 2'b01) state <= S3 ; 
				else if ({q0, qm1} == 2'b10) state <= S4 ;
				else state <= S5 ; 
		S3 	: 	state <= S5 ;
		S4 	: 	state <= S5 ;
		S5 	: 	#2 if (({q0, qm1} == 2'b01) && (!iszero))
					state <= S3 ;
				else if (({q0, qm1} == 2'b10) && (!iszero))
					state <= S4 ;
				else if (iszero)
					state <= S6 ;
		S6 	: 	state <= S6 ; 
	   	default:	state <= S0 ; 
	endcase 
			
	always @(state)
	
	//Assigning the control signals of the data path as per the state. 
	case (state)
		S0 	:  begin 								
				decr = 0 ;  ldcount = 0 ; shiftA = 0 ; ldA = 0 ; clrA = 0 ; ldM = 0 ;
 				ldQ =  0 ;  clrQ = 0 ;  shiftQ = 0 ; clrff  = 0 ; addsub = 0 ; done = 0;
			end 
		S1 	:  begin 
				clrA = 1 ; clrff = 1 ; ldcount = 1 ; ldM = 1 ;
			end 
		S2 	:  begin 
				clrA = 0 ; ldcount = 0 ; ldM = 0 ; ldQ = 1 ; decr = 0 ; 
              end 
		S3 	: begin 
				shiftA = 0 ; shiftQ = 0 ;ldQ = 0 ; addsub = 1 ; ldA = 1 ; decr = 0 ;
			end 
		S4 	: begin 
				shiftA = 0 ; shiftQ = 0 ;ldQ = 0 ; addsub = 0 ; ldA = 1 ; decr = 0 ;
			end 
		S5 	: begin
				clrff = 0; ldQ = 0 ; ldA = 0 ; shiftA = 1 ; shiftQ = 1 ; decr = 1 ;
			end 		 
		S6 	:   begin 
				shiftA = 0 ; shiftQ = 0 ; decr = 0 ; done = 1 ;
			end  
		default : begin 
				decr = 0 ;  ldcount = 0 ; shiftA = 0 ; ldA = 0 ; clrA = 0 ; ldM = 0 ;
 				ldQ =  0 ;  clrQ = 0 ;  shiftQ = 0 ; clrff  = 0 ; addsub = 0 ; done = 0;
			end  
	endcase 
endmodule 

// ==============================================================================================
// TVM : 

module Booths_Multiplier_tb ;
	//Port Section 
	reg clk ; 
	reg start ; 
	reg [4:0] data_in ;
	wire done ; 
	wire[1:0] temp;
	
	//Module Instantiation 
	booth_data_path	BOOTH_DP (iszero, qm1, q0, decr, ldcount, shiftA, ldA, clrA, ldM, ldQ, clrQ, shiftQ, clrff, data_in, addsub, clk) ;
	booth_control_path  BOOTH_CP (iszero, qm1, q0, decr, ldcount, shiftA, ldA, clrA, ldM, ldQ, clrQ, shiftQ, clrff, data_in, addsub, clk, start, done) ;

	initial 
		begin
			clk  = 1'b0 ;
			start = 1'b1;
		end 
	always 
		#5 clk = ~ clk ; 		// Clk of Time period 10 Time units. 
	initial 
		begin
			data_in = 7; 		// Value of M 
			#27 data_in = 8 ; 	// Value of Q 
		end 
		
	initial 
		begin 
			$dumpfile ("Booths.vcd") ; 
			$dumpvars (0, Booths_Multiplier_tb) ; 
			$display ("                                                   Booths Multiplier for Signed 4 Bit Numbers") ;
			$display ("                                                 Developed By : Debayan Mazumdar | Nishad Potdar") ;
			$monitor ($time , " | M: %5b | A: %5b |  Q: %5b | Q[-1]: %b | COUNT: %3b | ISZERO: %b | STATE: %3b | DONE: %b |",
					BOOTH_DP.M, BOOTH_DP.A, BOOTH_DP.Q, BOOTH_CP.qm1, BOOTH_DP.count, BOOTH_DP.iszero, BOOTH_CP.state, done) ; 
			#1000 $finish ;
		end
endmodule

// ==============================================================================================

Booths.vcd
$date
	Sat Sep 17 17:35:40 2022
$end
$version
	Icarus Verilog
$end
$timescale
	1s
$end
$scope module Booths_Multiplier_tb $end
$var wire 1 ! shiftQ $end
$var wire 1 " shiftA $end
$var wire 1 # qm1 $end
$var wire 1 $ q0 $end
$var wire 1 % ldcount $end
$var wire 1 & ldQ $end
$var wire 1 ' ldM $end
$var wire 1 ( ldA $end
$var wire 1 ) iszero $end
$var wire 1 * done $end
$var wire 1 + decr $end
$var wire 1 , clrff $end
$var wire 1 - clrQ $end
$var wire 1 . clrA $end
$var wire 1 / addsub $end
$var reg 1 0 clk $end
$var reg 5 1 data_in [4:0] $end
$var reg 1 2 start $end
$scope module BOOTH_CP $end
$var wire 1 0 clk $end
$var wire 5 3 data_in [4:0] $end
$var wire 1 2 start $end
$var wire 1 # qm1 $end
$var wire 1 $ q0 $end
$var wire 1 ) iszero $end
$var parameter 3 4 S0 $end
$var parameter 3 5 S1 $end
$var parameter 3 6 S2 $end
$var parameter 3 7 S3 $end
$var parameter 3 8 S4 $end
$var parameter 3 9 S5 $end
$var parameter 3 : S6 $end
$var reg 1 / addsub $end
$var reg 1 . clrA $end
$var reg 1 - clrQ $end
$var reg 1 , clrff $end
$var reg 1 + decr $end
$var reg 1 * done $end
$var reg 1 ( ldA $end
$var reg 1 ' ldM $end
$var reg 1 & ldQ $end
$var reg 1 % ldcount $end
$var reg 1 " shiftA $end
$var reg 1 ! shiftQ $end
$var reg 3 ; state [2:0] $end
$upscope $end
$scope module BOOTH_DP $end
$var wire 1 / addsub $end
$var wire 1 0 clk $end
$var wire 1 . clrA $end
$var wire 1 - clrQ $end
$var wire 1 , clrff $end
$var wire 5 < data_in [4:0] $end
$var wire 1 + decr $end
$var wire 1 ( ldA $end
$var wire 1 ' ldM $end
$var wire 1 & ldQ $end
$var wire 1 % ldcount $end
$var wire 1 " shiftA $end
$var wire 1 ! shiftQ $end
$var wire 1 # qm1 $end
$var wire 1 $ q0 $end
$var wire 1 ) iszero $end
$var wire 3 = count [2:0] $end
$var wire 5 > Z [4:0] $end
$var wire 5 ? Q [4:0] $end
$var wire 5 @ M [4:0] $end
$var wire 5 A A [4:0] $end
$scope module ALU $end
$var wire 1 / sel $end
$var wire 5 B b [4:0] $end
$var wire 5 C a [4:0] $end
$var reg 5 D out [4:0] $end
$upscope $end
$scope module ASR $end
$var wire 1 0 clk $end
$var wire 1 . clr $end
$var wire 5 E din [4:0] $end
$var wire 1 ( ld $end
$var wire 1 " shift $end
$var wire 1 F sin $end
$var reg 5 G dout [4:0] $end
$upscope $end
$scope module CNT $end
$var wire 1 0 clk $end
$var wire 1 + decC $end
$var wire 1 % ldC $end
$var reg 3 H cout [2:0] $end
$upscope $end
$scope module MPR $end
$var wire 1 0 clk $end
$var wire 1 ' ldP $end
$var wire 5 I pin [4:0] $end
$var reg 5 J pout [4:0] $end
$upscope $end
$scope module QM $end
$var wire 1 0 clk $end
$var wire 1 , clrd $end
$var wire 1 $ d $end
$var reg 1 # q $end
$upscope $end
$scope module QSR $end
$var wire 1 0 clk $end
$var wire 1 - clr $end
$var wire 5 K din [4:0] $end
$var wire 1 & ld $end
$var wire 1 ! shift $end
$var wire 1 L sin $end
$var reg 5 M dout [4:0] $end
$upscope $end
$upscope $end
$upscope $end
$enddefinitions $end
$comment Show the parameter values. $end
$dumpall
b110 :
b101 9
b100 8
b11 7
b10 6
b1 5
b0 4
$end
#0
$dumpvars
bx M
xL
b111 K
bx J
b111 I
bx H
bx G
xF
bx E
bx D
bx C
bx B
bx A
bx @
bx ?
bx >
bx =
b111 <
bx ;
b111 3
12
b111 1
00
x/
x.
x-
x,
x+
x*
x)
x(
x'
x&
x%
x$
x#
x"
x!
$end
#5
0*
0/
0,
0!
0-
0&
0'
0.
0(
0"
0%
0+
b0 ;
10
#10
00
#15
1'
1%
1,
1.
b1 ;
10
#20
00
#25
0F
0L
b11001 >
b11001 D
b11001 E
1&
0'
0%
0.
b0 A
b0 C
b0 G
b111 @
b111 B
b111 J
0#
0)
b101 =
b101 H
b10 ;
10
#27
b1000 1
b1000 3
b1000 <
b1000 I
b1000 K
#30
00
#35
0$
b1000 ?
b1000 M
10
#37
1+
1!
1"
0&
0,
b101 ;
#40
00
#45
b100 ?
b100 M
b100 =
b100 H
10
#50
00
#55
b11 =
b11 H
b10 ?
b10 M
10
#60
00
#65
1$
b1 ?
b1 M
b10 =
b10 H
10
#67
0+
1(
0!
0"
b100 ;
#70
00
#75
1F
1L
b10010 >
b10010 D
b10010 E
1+
1!
1"
0(
1#
b11001 A
b11001 C
b11001 G
b101 ;
10
#80
00
#85
0$
0L
b10101 >
b10101 D
b10101 E
b10000 ?
b10000 M
b11100 A
b11100 C
b11100 G
b1 =
b1 H
10
#87
b11 >
b11 D
b11 E
0+
1(
1/
0!
0"
b11 ;
#90
00
#95
0F
1L
b1010 >
b1010 D
b1010 E
1+
1!
1"
0(
0#
b11 A
b11 C
b11 G
b101 ;
10
#100
00
#105
b1000 >
b1000 D
b1000 E
b11000 ?
b11000 M
b1 A
b1 C
b1 G
1)
b0 =
b0 H
10
#107
1*
0+
0!
0"
b110 ;
